{
	// Key: Lua data key
	// Translation: visible header text for the column
	// DataType: enum for type of data (DataType_Float, DataType_String, DataType_ExporterVersion, DataType_CarName)
	
	"GeneralData": [
		{"ExporterVersion": {"Translation": "Exporter Version", "DataType": "DataType_ExporterVersion"}},
		{"GameVersion": {"Translation": "Game Version", "DataType": "DataType_Float"}},
		{"CarName": {"Translation": "Car Name", "DataType": "DataType_CarName"}}
	],
	
	
	"CarChoicesData": [
		{"ModelName": {"Translation": "Model Name", "DataType": "DataType_String"}},
		{"ModelYear": {"Translation": "Model Year", "DataType": "DataType_Float"}},
		{"BodyWheelbase": {"Translation": "Wheelbase", "DataType": "DataType_Float"}},
		{"ChassisType": {"Translation": "Chassis Type", "DataType": "DataType_String"}},
		{"ChassisMat": {"Translation": "Chassis Material", "DataType": "DataType_String"}},
		{"PanelMat": {"Translation": "Panel Material", "DataType": "DataType_String"}},
		{"SuspensionFront": {"Translation": "Front Suspension", "DataType": "DataType_String"}},
		{"SuspensionRear": {"Translation": "Rear Suspension", "DataType": "DataType_String"}},
		{"EnginePlacement": {"Translation": "Engine Placement", "DataType": "DataType_String"}},
		{"EngineOrientation": {"Translation": "Engine Orientation", "DataType": "DataType_String"}},
		{"ModelQualityBody": {"Translation": "Model Body Quality", "DataType": "DataType_Float"}},
		{"ModelQualityChassis": {"Translation": "Model Chassis Quality", "DataType": "DataType_Float"}},
		{"ModelTechpoolBody": {"Translation": "Model Body Techpool", "DataType": "DataType_Float"}},
		{"ModelTechpoolChassis": {"Translation": "Model Chassis Techpool", "DataType": "DataType_Float"}},
		{"TrimName": {"Translation": "Trim Name", "DataType": "DataType_String"}},
		{"TrimYear": {"Translation": "Trim Year", "DataType": "DataType_Float"}},
		//{"TrimQualityChassis": {"Translation": "Trim Chassis Quality", "DataType": "DataType_Float"}},
		{"TrimQualityBody": {"Translation": "Trim Body Quality", "DataType": "DataType_Float"}},
		{"TrimQualityAerodynamics": {"Translation": "Trim Aerodynamics Quality", "DataType": "DataType_Float"}},
		{"TrimQualityInterior": {"Translation": "Trim Interior Quality", "DataType": "DataType_Float"}},
		{"TrimQualityFixtures": {"Translation": "Trim Fixture Quality", "DataType": "DataType_Float"}},
		{"TrimQualityTyres": {"Translation": "Trim Tyre Quality", "DataType": "DataType_Float"}},
		{"TrimQualitySuspension": {"Translation": "Trim Suspension Quality", "DataType": "DataType_Float"}},
		{"TrimQualitySafety": {"Translation": "Trim Safety Quality", "DataType": "DataType_Float"}},
		{"TrimQualityBrakes": {"Translation": "Trim Brake Quality", "DataType": "DataType_Float"}},
		{"TrimQualityAssists": {"Translation": "Trim Assist Quality", "DataType": "DataType_Float"}},
		{"TrimQualityDrivetrain": {"Translation": "Trim Drivetrain Quality", "DataType": "DataType_Float"}},
		{"TrimTechpoolChassis": {"Translation": "Trim Chassis Techpool", "DataType": "DataType_Float"}},
		{"TrimTechpoolBody": {"Translation": "Trim Body Techpool", "DataType": "DataType_Float"}},
		{"TrimTechpoolAerodynamics": {"Translation": "Trim Aerodynamics Techpool", "DataType": "DataType_Float"}},
		{"TrimTechpoolInterior": {"Translation": "Trim Interior Techpool", "DataType": "DataType_Float"}},
		{"TrimTechpoolFixtures": {"Translation": "Trim Fixture Techpool", "DataType": "DataType_Float"}},
		{"TrimTechpoolTyres": {"Translation": "Trim Tyre Techpool", "DataType": "DataType_Float"}},
		{"TrimTechpoolSuspension": {"Translation": "Trim Suspension Techpool", "DataType": "DataType_Float"}},
		{"TrimTechpoolSafety": {"Translation": "Trim Safety Techpool", "DataType": "DataType_Float"}},
		{"TrimTechpoolBrakes": {"Translation": "Trim Brake Techpool", "DataType": "DataType_Float"}},
		{"TrimTechpoolAssists": {"Translation": "Trim Assist Techpool", "DataType": "DataType_Float"}},
		{"TrimTechpoolDrivetrain": {"Translation": "Trim Drivetrain Techpool", "DataType": "DataType_Float"}},
		{"BodyType": {"Translation": "Body Type", "DataType": "DataType_String"}},
		{"BodyDoors": {"Translation": "Doors", "DataType": "DataType_Float"}},
		{"BodyName": {"Translation": "Body Name", "DataType": "DataType_String"}},
		{"ConvertibleType": {"Translation": "Convertible Type", "DataType": "DataType_String"}},
		{"FrontSeatsFull": {"Translation": "Full 1st Row Seats", "DataType": "DataType_Float"}},
		{"FrontSeatsTemp": {"Translation": "Small 1st Row Seats", "DataType": "DataType_Float"}},
		{"MidSeatsFull": {"Translation": "Full 2nd Row Seats", "DataType": "DataType_Float"}},
		{"MidSeatsTemp": {"Translation": "Small 2nd Row Seats", "DataType": "DataType_Float"}},
		{"RearSeatsFull": {"Translation": "Full 3rd Row Seats", "DataType": "DataType_Float"}},
		{"RearSeatsTemp": {"Translation": "Small 3rd Row Seats", "DataType": "DataType_Float"}},
		{"DriveType": {"Translation": "Drive Type", "DataType": "DataType_String"}},
		{"GearboxType": {"Translation": "Gearbox Type", "DataType": "DataType_String"}},
		{"GearCount": {"Translation": "Gear Count", "DataType": "DataType_Float"}},
		{"GearSpacing": {"Translation": "Gear Spacing", "DataType": "DataType_Float"}},
		{"PowerDistribution": {"Translation": "Power To Front", "DataType": "DataType_Float"}},
		{"DiffType": {"Translation": "Differential Type", "DataType": "DataType_String"}},
		{"FinalDrive": {"Translation": "Final Drive", "DataType": "DataType_Float"}},
		{"SpeedLimit": {"Translation": "Speed Limiter", "DataType": "DataType_Float"}},
		{"ActiveCooling": {"Translation": "Active Cooling", "DataType": "DataType_String"}},
		{"Cooling": {"Translation": "Cooling Amount", "DataType": "DataType_Float"}},
		{"UnderTray": {"Translation": "Undertray", "DataType": "DataType_String"}},
		{"ActiveWing": {"Translation": "Active Aero", "DataType": "DataType_String"}},
		{"WingAngleRear": {"Translation": "Rear Wing Angle", "DataType": "DataType_Float"}},
		{"WingAngleFront": {"Translation": "Front Wing Angle", "DataType": "DataType_Float"}},
		{"Interior": {"Translation": "Interior", "DataType": "DataType_String"}},
		{"Entertainment": {"Translation": "Entertainment", "DataType": "DataType_String"}},
		{"PowerSteering": {"Translation": "Power Steering", "DataType": "DataType_String"}},
		{"AssistPackage": {"Translation": "Assists", "DataType": "DataType_String"}},
		{"Safety": {"Translation": "Safety", "DataType": "DataType_String"}},
		{"Springs": {"Translation": "Springs", "DataType": "DataType_String"}},
		{"FrontSpringStiffness": {"Translation": "Front Spring Stiffness", "DataType": "DataType_Float"}},
		{"RearSpringStiffness": {"Translation": "Rear Spring Stiffness", "DataType": "DataType_Float"}},
		{"Dampers": {"Translation": "Dampers", "DataType": "DataType_String"}},
		{"FrontDamperStiffness": {"Translation": "Front Damper Stiffness", "DataType": "DataType_Float"}},
		{"RearDamperStiffness": {"Translation": "Rear Damper Stiffness", "DataType": "DataType_Float"}},
		{"SwayBars": {"Translation": "Sway Bars", "DataType": "DataType_String"}},
		{"FrontARBStiffness": {"Translation": "Front Sway Bar Stiffness", "DataType": "DataType_Float"}},
		{"RearARBStiffness": {"Translation": "Rear Sway Bar Stiffness", "DataType": "DataType_Float"}},
		{"RideHeight": {"Translation": "Ride Height", "DataType": "DataType_Float"}},
		{"FrontCamber": {"Translation": "Front Camber", "DataType": "DataType_Float"}},
		{"RearCamber": {"Translation": "Rear Camber", "DataType": "DataType_Float"}},
		{"RimMaterial": {"Translation": "Rim Material", "DataType": "DataType_String"}},
		{"TyreType": {"Translation": "Tyre Type", "DataType": "DataType_String"}},
		{"TyreCompound": {"Translation": "Tyre Compound", "DataType": "DataType_String"}},
		{"FrontRimSize": {"Translation": "Front Rim Size", "DataType": "DataType_Float"}},
		{"RearRimSize": {"Translation": "Rear Rim Size", "DataType": "DataType_Float"}},
		{"FrontWheelOffset": {"Translation": "Front Wheel Offset", "DataType": "DataType_Float"}},
		{"RearWheelOffset": {"Translation": "Rear Wheel Offset", "DataType": "DataType_Float"}},
		{"FrontTyreProfile": {"Translation": "Front Tyre Profile", "DataType": "DataType_Float"}},
		{"RearTyreProfile": {"Translation": "Rear Tyre Profile", "DataType": "DataType_Float"}},
		{"FrontTyreWidth": {"Translation": "Front Tyre Width", "DataType": "DataType_Float"}},
		{"RearTyreWidth": {"Translation": "Rear Tyre Width", "DataType": "DataType_Float"}},
		{"FrontOverallDiameter": {"Translation": "Front Wheel Diameter", "DataType": "DataType_Float"}},
		{"RearOverallDiameter": {"Translation": "Rear Wheel Diameter", "DataType": "DataType_Float"}},
		{"FrontOverallDiameter": {"Translation": "Front Wheel Diameter", "DataType": "DataType_Float"}},
		{"RearOverallDiameter": {"Translation": "Rear Wheel Diameter", "DataType": "DataType_Float"}},
		{"FrontBrakeType": {"Translation": "Front Brake Type", "DataType": "DataType_String"}},
		{"RearBrakeType": {"Translation": "Rear Brake Type", "DataType": "DataType_String"}},
		{"FrontCaliperPistons": {"Translation": "Front Caliper Pistons", "DataType": "DataType_Float"}},
		{"RearCaliperPistons": {"Translation": "Rear Caliper Pistons", "DataType": "DataType_Float"}},
		{"FrontBrakeDiameter": {"Translation": "Front Brake Diameter", "DataType": "DataType_Float"}},
		{"RearBrakeDiameter": {"Translation": "Rear Brake Diameter", "DataType": "DataType_Float"}},
		{"FrontBrakePadType": {"Translation": "Front Brake Pad Type", "DataType": "DataType_Float"}},
		{"RearBrakePadType": {"Translation": "Rear Brake Pad Type", "DataType": "DataType_Float"}},
		{"FrontBrakeForce": {"Translation": "Front Brake Force", "DataType": "DataType_Float"}},
		{"RearBrakeForce": {"Translation": "Rear Brake Force", "DataType": "DataType_Float"}},
		{"WeightOptimizationTune": {"Translation": "Weight Optimization Tune", "DataType": "DataType_Float"}},
		{"WeightDistributionTune": {"Translation": "Weight Distribution Tune", "DataType": "DataType_Float"}}
	],
	
	
	"CarResultsData": [
		{"CarWeight": {"Translation": "Trim Weight", "DataType": "DataType_Float"}},
		{"TowWeight": {"Translation": "Tow Weight", "DataType": "DataType_Float"}},
		{"BodyStiffness": {"Translation": "Body Stiffness", "DataType": "DataType_Float"}},
		{"SportinessRating": {"Translation": "Sportiness Rating", "DataType": "DataType_Float"}},
		{"DrivabilityRating": {"Translation": "Drivability Rating", "DataType": "DataType_Float"}},
		{"UtilityRating": {"Translation": "Utility Rating", "DataType": "DataType_Float"}},
		{"EnvResistance": {"Translation": "Environmental Resistance", "DataType": "DataType_Float"}},
		{"Emissions": {"Translation": "Trim Emissions", "DataType": "DataType_Float"}},
		{"OffroadRating": {"Translation": "Offroad Rating", "DataType": "DataType_Float"}},
		{"PrestigeRating": {"Translation": "Prestige Rating", "DataType": "DataType_Float"}},
		{"ReliabilityRating": {"Translation": "Trim Reliability", "DataType": "DataType_Float"}},
		{"Economy": {"Translation": "Trim Economy", "DataType": "DataType_Float"}},
		{"PracticalityRating": {"Translation": "Practicality Rating", "DataType": "DataType_Float"}},
		{"SafetyRating": {"Translation": "Safety Rating", "DataType": "DataType_Float"}},
		{"ComfortRating": {"Translation": "Comfort Rating", "DataType": "DataType_Float"}},
		{"PassengerVolume": {"Translation": "Passenger Volume", "DataType": "DataType_Float"}},
		{"CargoVolume": {"Translation": "Cargo Volume", "DataType": "DataType_Float"}},
		{"TrimEngineeringTime": {"Translation": "Trim Engineering Time", "DataType": "DataType_Float"}},
		{"TrimManHours": {"Translation": "Trim Production Units", "DataType": "DataType_Float"}},
		{"TrimPrice": {"Translation": "Trim Price", "DataType": "DataType_Float"}},
		{"ToolingCosts": {"Translation": "Trim Tooling Costs", "DataType": "DataType_Float"}},
		{"ServiceCosts": {"Translation": "Trim Service Costs", "DataType": "DataType_Float"}},
		{"TotalTrimCosts": {"Translation": "Trim Total Costs", "DataType": "DataType_Float"}},
		{"TrimCost": {"Translation": "Trim Cost", "DataType": "DataType_Float"}},
		{"MatCost": {"Translation": "Trim Material Cost", "DataType": "DataType_Float"}},
		{"TrimEngCosts": {"Translation": "Trim Engineering Costs", "DataType": "DataType_Float"}},
		{"BrakingDistance": {"Translation": "Braking Distance", "DataType": "DataType_Float"}},
		{"MaxBodyRoll": {"Translation": "Max Body Roll", "DataType": "DataType_Float"}},
		{"Cornering": {"Translation": "Cornering", "DataType": "DataType_Float"}},
		{"FrontDownforce": {"Translation": "Front Downforce", "DataType": "DataType_Float"}},
		{"RearDownforce": {"Translation": "Rear Downforce", "DataType": "DataType_Float"}},
		{"TyreSpeedIndex": {"Translation": "Tyre Speed Index", "DataType": "DataType_String"}},
		{"TyreSpeedRating": {"Translation": "Tyre Speed Rating (km/h)", "DataType": "DataType_Float"}},
		{"TopSpeed": {"Translation": "Top Speed (km/h)", "DataType": "DataType_Float"}},
		{"TopSpeedGear": {"Translation": "Top Speed Gear", "DataType": "DataType_Float"}},
		{"TopSpeedEnginePower": {"Translation": "Top Speed Engine Power", "DataType": "DataType_Float"}},
		{"TopSpeedEngineRPM": {"Translation": "Top Speed Engine RPM", "DataType": "DataType_Float"}},
		{"SixtyTime": {"Translation": "60 Time", "DataType": "DataType_Float"}},
		{"EightyTime": {"Translation": "80 Time", "DataType": "DataType_Float"}},
		{"HundredTime": {"Translation": "100 Time", "DataType": "DataType_Float"}},
		{"TwoHundredTime": {"Translation": "200 Time", "DataType": "DataType_Float"}},
		{"HundredAndTwentyTime": {"Translation": "120 Time", "DataType": "DataType_Float"}},
		{"EightyToHundredAndTwentyTime": {"Translation": "80 To 120 Time", "DataType": "DataType_Float"}},
		{"KilometerTime": {"Translation": "Kilometer Time", "DataType": "DataType_Float"}},
		{"KilometerSpeed": {"Translation": "Kilometer Speed (km/h)", "DataType": "DataType_Float"}},
		{"QuarterMileTime": {"Translation": "1/4 Mile Time", "DataType": "DataType_Float"}},
		{"QuarterMileSpeed": {"Translation": "1/4 Mile Speed (km/h)", "DataType": "DataType_Float"}}
	],
	
	
	"EngineChoicesData": [
		{"FamilyName": {"Translation": "Engine Family Name", "DataType": "DataType_String"}},
		{"FamilyYear": {"Translation": "Engine Family Year", "DataType": "DataType_Float"}},
		{"FamilyQuality": {"Translation": "Family Quality", "DataType": "DataType_Float"}},
		{"FamilyTechpool": {"Translation": "Family Techpool", "DataType": "DataType_Float"}},
		//{"FamilyTopEndTechpool": {"Translation": "Family Top End Techpool", "DataType": "DataType_Float"}},
		{"FamilyBore": {"Translation": "Family Bore", "DataType": "DataType_Float"}},
		{"FamilyStroke": {"Translation": "Family Stroke", "DataType": "DataType_Float"}},
		{"FamilyDisplacement": {"Translation": "Family Displacement", "DataType": "DataType_Float"}},
		{"BlockType": {"Translation": "Block Type", "DataType": "DataType_String"}},
		{"Cylinders": {"Translation": "Cylinder Count", "DataType": "DataType_Float"}},
		{"BlockMaterial": {"Translation": "Block Material", "DataType": "DataType_String"}},
		{"HeadMaterial": {"Translation": "Head Material", "DataType": "DataType_String"}},
		{"HeadType": {"Translation": "Head Type", "DataType": "DataType_String"}},
		{"IntakeValves": {"Translation": "Intake Valves", "DataType": "DataType_Float"}},
		{"ExhaustValves": {"Translation": "Exhaust Valves", "DataType": "DataType_Float"}},
		{"VariantName": {"Translation": "Variant Name", "DataType": "DataType_String"}},
		{"VariantYear": {"Translation": "Variant Year", "DataType": "DataType_Float"}},
		{"VariantTopEndQuality": {"Translation": "Variant Top End Quality", "DataType": "DataType_Float"}},
		{"VariantBottomEndQuality": {"Translation": "Variant Bottom End Quality", "DataType": "DataType_Float"}},
		{"VariantAspirationQuality": {"Translation": "Variant Aspiration Quality", "DataType": "DataType_Float"}},
		{"VariantFuelSystemQuality": {"Translation": "Variant Fuel System Quality", "DataType": "DataType_Float"}},
		{"VariantExhaustQuality": {"Translation": "Variant Exhaust Quality", "DataType": "DataType_Float"}},
		{"VariantTopEndTechpool": {"Translation": "Variant Top End Techpool", "DataType": "DataType_Float"}},
		{"VariantFamilyTechpool": {"Translation": "Variant Family Techpool", "DataType": "DataType_Float"}},
		{"VariantBottomEndTechpool": {"Translation": "Variant Bottom End Techpool", "DataType": "DataType_Float"}},
		{"VariantAspirationTechpool": {"Translation": "Variant Aspiration Techpool", "DataType": "DataType_Float"}},
		{"VariantFuelSystemTechpool": {"Translation": "Variant Fuel System Techpool", "DataType": "DataType_Float"}},
		{"VariantExhaustTechpool": {"Translation": "Variant Exhaust Techpool", "DataType": "DataType_Float"}},
		{"VariantBore": {"Translation": "Variant Bore", "DataType": "DataType_Float"}},
		{"VariantStroke": {"Translation": "Variant Stroke", "DataType": "DataType_Float"}},
		{"VariantDisplacement": {"Translation": "Variant Displacement", "DataType": "DataType_Float"}},
		{"BalanceShaft": {"Translation": "Balance Shaft", "DataType": "DataType_String"}},
		{"BalancingMass": {"Translation": "Balancing Mass Setting", "DataType": "DataType_Float"}},
		{"Crankshaft": {"Translation": "Crankshaft", "DataType": "DataType_String"}},
		{"Conrods": {"Translation": "Conrods", "DataType": "DataType_String"}},
		{"Pistons": {"Translation": "Pistons", "DataType": "DataType_String"}},
		{"Compression": {"Translation": "Compression", "DataType": "DataType_Float"}},
		{"CamProfile": {"Translation": "Cam Profile", "DataType": "DataType_Float"}},
		{"ValveSpringStiffness": {"Translation": "Valve Spring Stiffness", "DataType": "DataType_Float"}},
		{"RPMLimit": {"Translation": "RPM Limit", "DataType": "DataType_Float"}},
		{"VVT": {"Translation": "VVT", "DataType": "DataType_String"}},
		{"VVL": {"Translation": "VVL", "DataType": "DataType_String"}},
		{"VVLCamProfile": {"Translation": "VVL Cam Profile", "DataType": "DataType_Float"}},
		{"VVLRPM": {"Translation": "VVL RPM", "DataType": "DataType_Float"}},
		{"Aspiration": {"Translation": "Aspiration", "DataType": "DataType_String"}},
		{"IntercoolerSize": {"Translation": "Intercooler Size", "DataType": "DataType_Float"}},
		{"AspirationItem1": {"Translation": "Aspiration Item 1", "DataType": "DataType_String"}},
		{"AspirationSubItem1": {"Translation": "Aspiration Sub Item 1", "DataType": "DataType_String"}},
		{"AspirationItem2": {"Translation": "Aspiration Item 2", "DataType": "DataType_String"}},
		{"AspirationSubItem2": {"Translation": "Aspiration Sub Item 2", "DataType": "DataType_String"}},
		{"BoostControl": {"Translation": "Boost Control", "DataType": "DataType_String"}},
		{"ChargerSize1": {"Translation": "Compressor Size 1", "DataType": "DataType_Float"}},
		{"ChargerSize2": {"Translation": "Compressor Size 2", "DataType": "DataType_Float"}},
		{"TurbineSize1": {"Translation": "Turbine Size 1", "DataType": "DataType_Float"}},
		{"TurbineSize2": {"Translation": "Turbine Size 2", "DataType": "DataType_Float"}},
		{"ChargerTune1": {"Translation": "Aspiration Tune 1", "DataType": "DataType_Float"}},
		{"ChargerTune2": {"Translation": "Aspiration Tune 2", "DataType": "DataType_Float"}},
		{"FuelSystemType": {"Translation": "Fuel System Type", "DataType": "DataType_String"}},
		{"FuelSystem": {"Translation": "Fuel System", "DataType": "DataType_String"}},
		{"Throttles": {"Translation": "Throttle Configuration", "DataType": "DataType_String"}},
		{"CarbSize": {"Translation": "Carb Size", "DataType": "DataType_Float"}},
		{"Intake": {"Translation": "Intake", "DataType": "DataType_String"}},
		{"IntakeSize": {"Translation": "Intake Size", "DataType": "DataType_Float"}},
		{"FuelLeaded": {"Translation": "Leaded Fuel", "DataType": "DataType_String"}},
		{"FuelType": {"Translation": "Fuel Type", "DataType": "DataType_String"}},
		{"FuelOctane": {"Translation": "Fuel Octane", "DataType": "DataType_Float"}},
		{"OctaneOffset": {"Translation": "Octane Offset", "DataType": "DataType_Float"}},
		//{"AFR": {"Translation": "AFR", "DataType": "DataType_Float"}},
		//{"IgnitionTiming": {"Translation": "Ignition Timing", "DataType": "DataType_Float"}},
		{"FuelMap": {"Translation": "Fuel Map", "DataType": "DataType_Float"}},
		{"Headers": {"Translation": "Headers", "DataType": "DataType_String"}},
		{"HeaderSize": {"Translation": "Header Size", "DataType": "DataType_Float"}},
		{"ExhaustCount": {"Translation": "Exhaust Count", "DataType": "DataType_String"}},
		{"ExhaustDiameter": {"Translation": "Exhaust Diameter", "DataType": "DataType_Float"}},
		{"BypassValves": {"Translation": "Exhaust Bypass Valves", "DataType": "DataType_String"}},
		{"Cat": {"Translation": "Catalytic Converter", "DataType": "DataType_String"}},
		{"Muffler1": {"Translation": "Muffler 1", "DataType": "DataType_String"}},
		{"Muffler2": {"Translation": "Muffler 2", "DataType": "DataType_String"}}
	],
	
	
	"EngineResultsData": [
		{"EnginePower": {"Translation": "Peak Power", "DataType": "DataType_Float"}},
		{"EnginePowerRPM": {"Translation": "Peak Power RPM", "DataType": "DataType_Float"}},
		{"EngineTorque": {"Translation": "Peak Torque", "DataType": "DataType_Float"}},
		{"EngineTorqueRPM": {"Translation": "Peak Torque RPM", "DataType": "DataType_Float"}},
		{"EnginePeakBoost": {"Translation": "Peak Boost", "DataType": "DataType_Float"}},
		{"EnginePeakBoostRPM": {"Translation": "Peak Boost RPM", "DataType": "DataType_Float"}},
		{"EngineIdleRPM": {"Translation": "Idle RPM", "DataType": "DataType_Float"}},
		{"EngineMaxRPM": {"Translation": "Max RPM", "DataType": "DataType_Float"}},
		//{"MinEconomyRPM": {"Translation": "Min Economy RPM", "DataType": "DataType_Float"}},
		{"EngineWeight": {"Translation": "Engine Weight", "DataType": "DataType_Float"}},
		{"EngineFlywheelWeight": {"Translation": "Flywheel Weight", "DataType": "DataType_Float"}},
		{"EngineRequiredCooling": {"Translation": "Required Cooling", "DataType": "DataType_Float"}},
		{"EnginePerformanceIndex": {"Translation": "Engine Performance Index", "DataType": "DataType_Float"}},
		{"EngineResponsiveness": {"Translation": "Engine Responsiveness", "DataType": "DataType_Float"}},
		{"EngineSmoothness": {"Translation": "Engine Smoothness", "DataType": "DataType_Float"}},
		{"EngineReliability": {"Translation": "Engine Reliability", "DataType": "DataType_Float"}},
		
		{"WES": {"Translation": "WES", "DataType": "DataType_String"}},
		
		{"CO": {"Translation": "WLTP Class 3 CO", "DataType": "DataType_Float"}},
		{"COPerKm": {"Translation": "WLTP Class 3 CO Per KM", "DataType": "DataType_Float"}},
		
		{"NOx": {"Translation": "WLTP Class 3 NOx", "DataType": "DataType_Float"}},
		{"NOxPerKm": {"Translation": "WLTP Class 3 NOx Per KM", "DataType": "DataType_Float"}},
		
		{"HC": {"Translation": "WLTP Class 3 HC", "DataType": "DataType_Float"}},
		{"HCPerKm": {"Translation": "WLTP Class 3 HC Per KM", "DataType": "DataType_Float"}},
		//{"EngineEmissions": {"Translation": "Engine Emissions", "DataType": "DataType_Float"}},
		
		{"EngineEfficiency": {"Translation": "Engine Efficiency", "DataType": "DataType_Float"}},
		{"EngineNoise": {"Translation": "Engine Noise", "DataType": "DataType_Float"}},
		{"IntakeNoise": {"Translation": "Intake Noise", "DataType": "DataType_Float"}},
		{"ExhaustNoise": {"Translation": "Exhaust Noise", "DataType": "DataType_Float"}},
		{"EngineRONResult": {"Translation": "Engine RON Rating", "DataType": "DataType_Float"}},
		{"EngineEngineeringTime": {"Translation": "Engine Engineering Time", "DataType": "DataType_Float"}},
		{"EngineProductionUnits": {"Translation": "Engine Production Units", "DataType": "DataType_Float"}},
		{"EngineEngineeringCost": {"Translation": "Engine Engineering Costs", "DataType": "DataType_Float"}},
		{"EngineToolingCosts": {"Translation": "Engine Tooling Costs", "DataType": "DataType_Float"}},
		{"EngineMaterialCost": {"Translation": "Engine Material Cost", "DataType": "DataType_Float"}},
		{"EngineTotalCost": {"Translation": "Engine Total Cost", "DataType": "DataType_Float"}},
		{"EngineServiceCost": {"Translation": "Engine Service Cost", "DataType": "DataType_Float"}},
		{"CrankMaxRPM": {"Translation": "Crankshaft Max RPM", "DataType": "DataType_Float"}},
		{"CrankMaxTorque": {"Translation": "Crankshaft Max Torque", "DataType": "DataType_Float"}},
		{"ConrodMaxRPM": {"Translation": "Conrods Max RPM", "DataType": "DataType_Float"}},
		{"ConrodMaxTorque": {"Translation": "Conrods Max Torque", "DataType": "DataType_Float"}},
		{"PistonMaxRPM": {"Translation": "Pistons Max RPM", "DataType": "DataType_Float"}},
		{"PistonMaxTorque": {"Translation": "Pistons Max Torque", "DataType": "DataType_Float"}}
	]
}